[{"Id":1,"Cedula":"40218314058","Nombres":"Pazzis","Apellidos":"Paulino","LugarNacimiento":"Santo Domingo","FechaNacimiento":"2003-06-20T12:27:22","Nacionalidad":"Dominicana","Sexo":"M","Sangre":"A+","EstadoCivil":"Casado","FechaExpiracion":"2024-06-26T12:27:22","URLFoto":"C:\\Users\\pazzi\\Downloads\\WhatsApp Image 2022-04-29 at 2.10.15 AM.jpeg","CedulaAnterior":"00000000000","ColegioElectoral":1105,"UbicacionColegio":"Colegio Cardenal Sancha","DireccionResidencia":"Residencial Amelia XVII","Sector":"Alma Rosa I","Municipio":"Santo Domingo Este","RegistroNacimiento":"11344-23422-121","CodigoPostal":1105,"FechaRegistro":"2022-06-23T14:11:02.12307-04:00"},{"Id":3,"Cedula":"23456543223","Nombres":"12345","Apellidos":"2345","LugarNacimiento":"23456765","FechaNacimiento":"2022-06-23T14:20:16.8110701-04:00","Nacionalidad":"23456765","Sexo":"M","Sangre":"A+","EstadoCivil":"Soltero","FechaExpiracion":"2022-06-23T14:20:16.8001003-04:00","URLFoto":"","CedulaAnterior":"12345678765","ColegioElectoral":2345,"UbicacionColegio":"2345678","DireccionResidencia":"34567","Sector":"123456","Municipio":"123456","RegistroNacimiento":"234567654","CodigoPostal":2345,"FechaRegistro":"2022-06-23T14:21:56.4054496-04:00"},{"Id":4,"Cedula":"52636962024","Nombres":"Anne Marie ","Apellidos":"Joaquin Gonzalez","LugarNacimiento":"Santiago","FechaNacimiento":"2003-10-03T12:27:22","Nacionalidad":"dominicana","Sexo":"F","Sangre":"O+","EstadoCivil":"Soltero","FechaExpiracion":"2024-06-26T12:27:22","URLFoto":"C:\\Users\\pazzi\\Downloads\\WhatsApp Image 2022-04-29 at 3.45.59 PM.jpeg","CedulaAnterior":"","ColegioElectoral":63635,"UbicacionColegio":"Santiago","DireccionResidencia":"santiago","Sector":"santiago","Municipio":"santiago","RegistroNacimiento":"253253253245","CodigoPostal":63635,"FechaRegistro":"2022-06-23T14:22:43.0325752-04:00"}]